cpp_include_lint/__init__.py
cpp_include_lint/__main__.py
cpp_include_lint-0.2.dist-info/LICENSE
cpp_include_lint-0.2.dist-info/METADATA
cpp_include_lint-0.2.dist-info/WHEEL
cpp_include_lint-0.2.dist-info/entry_points.txt
cpp_include_lint-0.2.dist-info/top_level.txt
cpp_include_lint-0.2.dist-info/RECORD
