Metadata-Version: 2.1
Name: cpp-include-lint
Version: 0.2
Summary: Sort #include directives of C/C++ files
Home-page: https://github.com/Docheinstein/cpp-include-lint
Author: Stefano Dottore
Author-email: docheinstein@gmail.com
License: MIT
Keywords: c cpp include lint sort
Platform: UNKNOWN
Requires-Python: >=3.7
License-File: LICENSE
